CHANGES.txt
CONTRIBUTORS.txt
MANIFEST.in
README.txt
setup.cfg
setup.py
docs/HISTORY.txt
docs/INSTALL.txt
docs/LICENSE.GPL
docs/LICENSE.txt
uwosh/__init__.py
uwosh.meeting.egg-info/PKG-INFO
uwosh.meeting.egg-info/SOURCES.txt
uwosh.meeting.egg-info/dependency_links.txt
uwosh.meeting.egg-info/entry_points.txt
uwosh.meeting.egg-info/namespace_packages.txt
uwosh.meeting.egg-info/not-zip-safe
uwosh.meeting.egg-info/paster_plugins.txt
uwosh.meeting.egg-info/requires.txt
uwosh.meeting.egg-info/top_level.txt
uwosh/meeting/README.txt
uwosh/meeting/__init__.py
uwosh/meeting/config.py
uwosh/meeting/configure.zcml
uwosh/meeting/setuphandlers.py
uwosh/meeting/skins.zcml
uwosh/meeting/browser/__init__.py
uwosh/meeting/browser/configure.zcml
uwosh/meeting/content/__init__.py
uwosh/meeting/content/configure.zcml
uwosh/meeting/content/meeting.py
uwosh/meeting/interfaces/__init__.py
uwosh/meeting/interfaces/meeting.py
uwosh/meeting/portlets/__init__.py
uwosh/meeting/portlets/configure.zcml
uwosh/meeting/profiles/default/factorytool.xml
uwosh/meeting/profiles/default/metadata.xml
uwosh/meeting/profiles/default/portlets.xml
uwosh/meeting/profiles/default/rolemap.xml
uwosh/meeting/profiles/default/skins.xml
uwosh/meeting/profiles/default/types.xml
uwosh/meeting/profiles/default/uwosh.meeting_various.txt
uwosh/meeting/profiles/default/types/Meeting.xml
uwosh/meeting/profiles/uninstall/skins.xml
uwosh/meeting/skins/uwosh_meeting_custom_templates/SFLight_meeting_view.pt
uwosh/meeting/skins/uwosh_meeting_custom_templates/backreferencebrowserwidget.pt
uwosh/meeting/skins/uwosh_meeting_custom_templates/backreferencewidget.pt
uwosh/meeting/skins/uwosh_meeting_custom_templates/meeting_view.pt
uwosh/meeting/skins/uwosh_meeting_custom_templates/meeting_view.pt.metadata
uwosh/meeting/tests/__init__.py
uwosh/meeting/tests/base.py
uwosh/meeting/tests/test_all.py
uwosh/meeting/tests/test_doctest.py