Metadata-Version: 1.0
Name: uwosh.meeting
Version: 0.5
Summary: a folderish Event that centralizes meeting information
Home-page: https://svn.it.uwosh.edu/svn/plone/Projects/uwosh.meeting/
Author: T. Kim Nguyen
Author-email: nguyen@uwosh.edu
License: GPL
Keywords: meeting,event,folder,attachment,minutes,agenda,action items
Platform: UNKNOWN
Classifier: Framework :: Plone
Classifier: Intended Audience :: Developers
Classifier: License :: OSI Approved :: GNU General Public License (GPL)
